sdmbc/__init__.py
sdmbc/analysis_plot.py
sdmbc/bias_correction.py
sdmbc/figurefunction.py
sdmbc/main_biascorrection.exe
sdmbc/output_reformatter.py
sdmbc/user_input.py
tests/__init__.py
tests/analysis_plot.py
tests/bias_correction.py
tests/figurefunction.py
tests/output_reformatter.py
sdmbc-0.1.1.dist-info/LICENSE
sdmbc-0.1.1.dist-info/METADATA
sdmbc-0.1.1.dist-info/WHEEL
sdmbc-0.1.1.dist-info/top_level.txt
sdmbc-0.1.1.dist-info/RECORD
